{
  "hash": "7ee10731",
  "configHash": "27bc65ed",
  "lockfileHash": "815a2d32",
  "browserHash": "4934a31e",
  "optimized": {
    "react": {
      "src": "../../node_modules/react/index.js",
      "file": "react.js",
      "fileHash": "113b8620",
      "needsInterop": true
    },
    "react-dom/client": {
      "src": "../../node_modules/react-dom/client.js",
      "file": "react-dom_client.js",
      "fileHash": "cf135557",
      "needsInterop": true
    },
    "react-router-dom": {
      "src": "../../node_modules/react-router-dom/dist/index.mjs",
      "file": "react-router-dom.js",
      "fileHash": "e644243b",
      "needsInterop": false
    },
    "lucide-react": {
      "src": "../../node_modules/lucide-react/dist/esm/lucide-react.js",
      "file": "lucide-react.js",
      "fileHash": "954cded5",
      "needsInterop": false
    },
    "zustand": {
      "src": "../../node_modules/zustand/esm/index.mjs",
      "file": "zustand.js",
      "fileHash": "7dc46dff",
      "needsInterop": false
    },
    "axios": {
      "src": "../../node_modules/axios/index.js",
      "file": "axios.js",
      "fileHash": "8813216e",
      "needsInterop": false
    }
  },
  "chunks": {
    "chunk-5HNGYYSW": {
      "file": "chunk-5HNGYYSW.js"
    },
    "chunk-TVFQMRVC": {
      "file": "chunk-TVFQMRVC.js"
    },
    "chunk-G3PMV62Z": {
      "file": "chunk-G3PMV62Z.js"
    }
  }
}